document_data_extractor-1.0.4.dist-info/licenses/LICENSE
document_extractor/__init__.py
document_extractor/cli.py
document_extractor/config.py
document_extractor/exceptions.py
document_extractor/extractor.py
document_extractor/result.py
document_extractor/__pycache__/__init__.cpython-310.pyc
document_extractor/__pycache__/__init__.cpython-37.pyc
document_extractor/__pycache__/config.cpython-310.pyc
document_extractor/__pycache__/config.cpython-37.pyc
document_extractor/__pycache__/exceptions.cpython-310.pyc
document_extractor/__pycache__/exceptions.cpython-37.pyc
document_extractor/__pycache__/extractor.cpython-310.pyc
document_extractor/__pycache__/extractor.cpython-37.pyc
document_extractor/__pycache__/result.cpython-310.pyc
document_extractor/__pycache__/result.cpython-37.pyc
document_extractor/pipeline/__init__.py
document_extractor/pipeline/layout_detector.py
document_extractor/pipeline/model_downloader.py
document_extractor/pipeline/nanonets_processor.py
document_extractor/pipeline/neural_document_processor.py
document_extractor/pipeline/ocr_service.py
document_extractor/pipeline/__pycache__/__init__.cpython-310.pyc
document_extractor/pipeline/__pycache__/__init__.cpython-37.pyc
document_extractor/pipeline/__pycache__/layout_detector.cpython-310.pyc
document_extractor/pipeline/__pycache__/layout_detector.cpython-37.pyc
document_extractor/pipeline/__pycache__/model_downloader.cpython-310.pyc
document_extractor/pipeline/__pycache__/model_downloader.cpython-37.pyc
document_extractor/pipeline/__pycache__/neural_document_processor.cpython-310.pyc
document_extractor/pipeline/__pycache__/neural_document_processor.cpython-37.pyc
document_extractor/pipeline/__pycache__/ocr_service.cpython-310.pyc
document_extractor/pipeline/__pycache__/ocr_service.cpython-37.pyc
document_extractor/processors/__init__.py
document_extractor/processors/base.py
document_extractor/processors/cloud_processor.py
document_extractor/processors/docx_processor.py
document_extractor/processors/excel_processor.py
document_data_extractor-1.0.4.dist-info/METADATA
document_data_extractor-1.0.4.dist-info/WHEEL
document_data_extractor-1.0.4.dist-info/entry_points.txt
document_data_extractor-1.0.4.dist-info/top_level.txt
document_data_extractor-1.0.4.dist-info/RECORD
