Metadata-Version: 2.4
Name: document-data-extractor
Version: 1.0.4
Summary: Best open-source document to markdown extractor for LLM training data. Convert PDF, Word, PowerPoint, Excel, images, URLs to clean markdown, JSON, HTML locally. Alternative to Unstructured, Docling, Marker, MarkItDown, MinerU, PaddleOCR, Tesseract
Author-email: Nanonets <team@nanonets.com>
License: MIT
Project-URL: Homepage, https://github.com/nanonets/llm-data-converter
Project-URL: Repository, https://github.com/nanonets/llm-data-converter
Project-URL: Documentation, https://github.com/nanonets/llm-data-converter#readme
Project-URL: Issues, https://github.com/nanonets/llm-data-converter/issues
Keywords: llm,document-processing,document-conversion,markdown,pdf,image-processing,intelligent-document-processing,document-understanding,ocr,rag,ai-training-data,unstructured-alternative,docling-alternative,marker-alternative,markitdown-alternative,mineru-alternative,paddleocr-alternative,tesseract-alternative,document-to-markdown,pdf-to-markdown,local-document-processing,offline-document-extractor,structured-data-extraction,table-extraction,layout-detection,llm-ready-data,document-ai,text-ext
Classifier: Development Status :: 4 - Beta
Classifier: Intended Audience :: Developers
Classifier: License :: OSI Approved :: MIT License
Classifier: Programming Language :: Python :: 3
Classifier: Programming Language :: Python :: 3.8
Classifier: Programming Language :: Python :: 3.9
Classifier: Programming Language :: Python :: 3.10
Classifier: Programming Language :: Python :: 3.11
Classifier: Programming Language :: Python :: 3.12
Classifier: Topic :: Scientific/Engineering :: Artificial Intelligence
Classifier: Topic :: Software Development :: Libraries :: Python Modules
Classifier: Topic :: Text Processing :: Markup
Classifier: Topic :: Multimedia :: Graphics :: Graphics Conversion
Requires-Python: >=3.8
License-File: LICENSE
Requires-Dist: Pillow>=9.0.0
Requires-Dist: pdf2image>=1.17.0
Requires-Dist: markdownify>=0.11.6
Requires-Dist: requests>=2.25.0
Requires-Dist: beautifulsoup4>=4.9.0
Requires-Dist: lxml>=4.6.0
Requires-Dist: python-docx>=0.8.11
Requires-Dist: python-pptx>=0.6.21
Requires-Dist: pypandoc>=1.11
Requires-Dist: openpyxl>=3.0.0
Requires-Dist: pandas>=1.3.0
Requires-Dist: numpy<2.0.0,>=1.21.0
Requires-Dist: PyMuPDF>=1.23.0
Requires-Dist: docling-ibm-models>=0.1.0
Requires-Dist: easyocr>=1.7.0
Requires-Dist: huggingface_hub>=0.23.0
Requires-Dist: tqdm>=4.64.0
Requires-Dist: transformers<4.50.0,>=4.20.0; python_version <= "3.8"
Requires-Dist: tokenizers<0.20.0,>=0.13.0; python_version <= "3.8"
Requires-Dist: setuptools>=65.0.0; python_version <= "3.8"
Requires-Dist: wheel>=0.37.0; python_version <= "3.8"
Requires-Dist: transformers>=4.20.0; python_version >= "3.9"
Requires-Dist: tokenizers>=0.13.0; python_version >= "3.9"
Provides-Extra: dev
Requires-Dist: pytest>=6.0.0; extra == "dev"
Requires-Dist: pytest-cov>=2.10.0; extra == "dev"
Requires-Dist: black>=21.0.0; extra == "dev"
Requires-Dist: flake8>=3.8.0; extra == "dev"
Requires-Dist: mypy>=0.800; extra == "dev"
Provides-Extra: local-llm
Requires-Dist: ollama>=0.5.0; extra == "local-llm"
Dynamic: license-file
